textprep
