Metadata-Version: 2.1
Name: textprep
Version: 0.0.3
Summary: One-stop text preprocessing package for NLP algorithm.
Home-page: https://github.com/xga0/textprep-packagee
Author: Sean Gao
Author-email: seangaoxy@gmail.com
License: UNKNOWN
Platform: UNKNOWN
Classifier: Programming Language :: Python :: 3
Classifier: License :: OSI Approved :: MIT License
Classifier: Operating System :: OS Independent
Requires-Python: >=3.6
